<?xml version="1.0" encoding="UTF-8"?>
<Entity version="2" CardID="NAX9_06">
  <MasterPower>ad62653d-2dab-408b-b651-b67606bdb9e5</MasterPower>
  <Tag name="CardName" enumID="185" type="String">
    <enUS>Unholy Shadow</enUS>
    <zhTW>邪惡暗影</zhTW>
    <zhCN>邪恶之影</zhCN>
    <ruRU>Нечестивая тень</ruRU>
    <ptBR>Sombra Profana</ptBR>
    <plPL>Przeklęty cień</plPL>
    <koKR>부정의 그림자</koKR>
    <itIT>Ombra Empia</itIT>
    <frFR>Ombre impie</frFR>
    <esMX>Sombra impía</esMX>
    <esES>Sombra impía</esES>
    <deDE>Unheiliger Schatten</deDE>
  </Tag>
  <Tag name="CardSet" enumID="183" type="CardSet" value="12" />
  <Tag name="CardType" enumID="202" type="CardType" value="10" />
  <Tag name="Cost" enumID="48" type="Number" value="5" />
  <Tag name="CardTextInHand" enumID="184" type="String">
    <enUS>&lt;b&gt;Hero Power&lt;/b&gt;\nDraw 2 cards.</enUS>
    <zhTW>&lt;b&gt;英雄能力&lt;/b&gt;\n抽2張牌</zhTW>
    <zhCN>&lt;b&gt;英雄技能&lt;/b&gt;\n抽两张牌。</zhCN>
    <ruRU>&lt;b&gt;Сила героя&lt;/b&gt;\n Берет 2 карты.</ruRU>
    <ptBR>&lt;b&gt;Poder Heroico&lt;/b&gt;\nCompre 2 cards.</ptBR>
    <plPL>&lt;b&gt;Moc specjalna&lt;/b&gt;\nDobierz 2 karty.</plPL>
    <koKR>&lt;b&gt;영웅 능력&lt;/b&gt;\n카드를 2장 뽑습니다.</koKR>
    <itIT>&lt;b&gt;Potere Eroe&lt;/b&gt;\nPesca 2 carte.</itIT>
    <frFR>&lt;b&gt;Pouvoir héroïque&lt;/b&gt;\nPioche deux cartes.</frFR>
    <esMX>&lt;b&gt;Poder de héroe&lt;/b&gt;\nRoba 2 cartas.</esMX>
    <esES>&lt;b&gt;Poder de héroe&lt;/b&gt;\nRoba 2 cartas.</esES>
    <deDE>&lt;b&gt;Heldenfähigkeit&lt;/b&gt;\nZieht 2 Karten.</deDE>
  </Tag>
  <Tag name="EnchantmentBirthVisual" enumID="330" type="EnchantmentVisualType" value="0" />
  <Tag name="EnchantmentIdleVisual" enumID="331" type="EnchantmentVisualType" value="0" />
  <Power definition="ad62653d-2dab-408b-b651-b67606bdb9e5" />
</Entity>